{
  "timestamp": "2026-07-16T19:30:59.586Z",
  "live": [
    {
      "username": "Kitboga",
      "title": "Hunting Scammers [Ep. 1541]",
      "game": "Just Chatting",
      "started_at": "2026-07-16T16:50:50Z"
    },
    {
      "username": "AlveusSanctuary",
      "title": "Animal Ambassador 24/7 Live Cams | !alveus !institute !pixel !schedule !video",
      "game": "Animals, Aquariums, and Zoos",
      "started_at": "2026-07-15T13:01:46Z"
    },
    {
      "username": "EJ_SA",
      "title": "EJ'S SPACEX STARSHIP FLIGHT 13 LAUNCH COVERAGE! 7/16/26",
      "game": "Science & Technology",
      "started_at": "2026-07-16T13:50:33Z"
    },
    {
      "username": "SciAnts_Streams",
      "title": "Resident Evil 5:  Science behind the Uroboros Virus | Collab with @kimmydnc | 🏴‍☠️🏴‍☠️ later | Partner+ 148/300 | !ppp !yt !pod",
      "game": "Resident Evil 5",
      "started_at": "2026-07-16T16:00:55Z"
    },
    {
      "username": "oh_bother",
      "title": "Meet Momo the cowboy robot... lawn mower. Momo let the magic smoke go, so we gotta see what broke.",
      "game": "Science & Technology",
      "started_at": "2026-07-16T16:30:28Z"
    },
    {
      "username": "Zachap",
      "title": "people complain about brainrot, then enable it as if it wasn't optional. why does everyone feel they have to be a sacrificial lamb?",
      "game": "Politics",
      "started_at": "2026-07-16T09:59:27Z"
    },
    {
      "username": "DrMick",
      "title": "Mental Health Chat + Painting 40k",
      "game": "Miniatures & Models",
      "started_at": "2026-07-16T19:06:46Z"
    },
    {
      "username": "IrishJohnGames",
      "title": "🍀 Rise of Piracy dev! | !charity !rop !patreon !discord",
      "game": "",
      "started_at": "2026-07-16T18:09:12Z"
    },
    {
      "username": "SydHeresy",
      "title": "Did Someone Say Soldering",
      "game": "Science & Technology",
      "started_at": "2026-07-16T18:00:18Z"
    },
    {
      "username": "eToThe2iPi",
      "title": "Matter + Potential: Electricity & Magnetism Study Group",
      "game": "Science & Technology",
      "started_at": "2026-07-16T18:00:01Z"
    },
    {
      "username": "Rocketology",
      "title": "1/4 Real Scale Kareer - Episode 3 Starship Launch Coverage Later",
      "game": "Kerbal Space Program",
      "started_at": "2026-07-16T18:45:56Z"
    },
    {
      "username": "ActualEducation",
      "title": "Physics 1B",
      "game": "Just Chatting",
      "started_at": "2026-07-16T19:29:35Z"
    }
  ]
}