{
  "timestamp": "2026-05-23T21:12:07.286Z",
  "live": [
    {
      "username": "AlveusSanctuary",
      "title": "Animal Ambassador 24/7 Live Cams | !alveus !institute !pixel !schedule !video",
      "game": "Animals, Aquariums, and Zoos",
      "started_at": "2026-05-23T05:36:22Z"
    },
    {
      "username": "Rocketology",
      "title": "UnKerbaled Start 50% Science Kareer Kontinued",
      "game": "Kerbal Space Program",
      "started_at": "2026-05-23T17:54:11Z"
    },
    {
      "username": "SydHeresy",
      "title": "More Parts - More Electronics - More Synths",
      "game": "Science & Technology",
      "started_at": "2026-05-23T19:00:20Z"
    },
    {
      "username": "DonFactorial",
      "title": "Answering your math questions and working on the never-ending PDEs",
      "game": "Math",
      "started_at": "2026-05-23T19:14:30Z"
    }
  ]
}