{
  "timestamp": "2026-07-01T00:16:04.235Z",
  "live": [
    {
      "username": "AlveusSanctuary",
      "title": "Alveus Subathon (Day 38 / 43+) | !alveus !institute !pixel !schedule !video !census !subathon",
      "game": "Just Chatting",
      "started_at": "2026-06-29T13:01:24Z"
    },
    {
      "username": "imreallyimportant",
      "title": "LAST DAY OF THE JUNE 2028 POLL | SC REJECTS TRUMP'S EFFORT TO END BIRTHRIGHT CITIZENSHIP",
      "game": "Just Chatting",
      "started_at": "2026-06-30T21:49:41Z"
    },
    {
      "username": "Moohoodles",
      "title": "☄️Asteroid Day charity stream for The Planetary Society! ☄️ !casey !tps !defense",
      "game": "Science & Technology",
      "started_at": "2026-06-30T23:47:07Z"
    },
    {
      "username": "AstroCanuck",
      "title": "Astro's Po'Pourri: Final Day of June Extravaganza! | !35 !PGV !nail | !drop !tkf",
      "game": "Lego & Brickbuilding",
      "started_at": "2026-06-30T23:05:45Z"
    },
    {
      "username": "shnaff",
      "title": "Guitar, piano, and singing in !stereo🎧",
      "game": "Music",
      "started_at": "2026-06-30T22:01:50Z"
    },
    {
      "username": "SydHeresy",
      "title": "Electronics LYFE - Soldering And Synthesizers",
      "game": "Science & Technology",
      "started_at": "2026-06-30T18:31:17Z"
    },
    {
      "username": "eToThe2iPi",
      "title": "Multivariable Calculus Review! Line Integrals + Surface Integrals (maybe)",
      "game": "Math",
      "started_at": "2026-06-30T21:57:51Z"
    },
    {
      "username": "MelissaInDeNile",
      "title": "How long will it take us to complete the Homesteading Missions in AC:III?? ~ Follower Goal: 2379/2600 ~ !socials !beyonddenile",
      "game": "Assassin's Creed III Remastered",
      "started_at": "2026-06-30T22:50:31Z"
    },
    {
      "username": "nSimplexPachinko",
      "title": "Back to The Gallery, Using The Pawn; Starting Day 33; Night 15, Blue Prince - 20260630",
      "game": "Blue Prince",
      "started_at": "2026-06-30T20:33:23Z"
    }
  ]
}