{
  "timestamp": "2026-03-13T06:08:29.876Z",
  "live": [
    {
      "username": "AlveusSanctuary",
      "title": "Animal Ambassador 24/7 Live Cams | !alveus !institute !pixel !schedule !video !feed",
      "game": "Animals, Aquariums, and Zoos",
      "started_at": "2026-03-11T14:32:21Z"
    },
    {
      "username": "SydHeresy",
      "title": "Back From The Road - Parts Are In - Soldering - Electronics",
      "game": "Science & Technology",
      "started_at": "2026-03-12T21:00:18Z"
    },
    {
      "username": "happyknightmares",
      "title": "Art stream! Drawing more synesthesia 🧠✍️🌈(Featuring Big_Duckie_Snow in the background!🐤)",
      "game": "Art",
      "started_at": "2026-03-13T05:10:14Z"
    },
    {
      "username": "walkingsticklibrary",
      "title": "The business of bushmeat, down and dirty with type 2 diabetes, and ecosystem services provided by woodpeckers.",
      "game": "IRL",
      "started_at": "2026-03-13T01:37:18Z"
    }
  ]
}