{
  "timestamp": "2026-03-24T08:07:16.617Z",
  "live": [
    {
      "username": "AlveusSanctuary",
      "title": "Animal Ambassador 24/7 Live Cams | !alveus !institute !pixel !schedule !video !feed",
      "game": "Animals, Aquariums, and Zoos",
      "started_at": "2026-03-23T15:24:58Z"
    },
    {
      "username": "Moohoodles",
      "title": "🪐 Palia chillin ✨ Plus Program pushin !pp",
      "game": "Palia",
      "started_at": "2026-03-24T01:17:36Z"
    },
    {
      "username": "DrMick",
      "title": "Mental Health Chat + Painting 40k",
      "game": "Miniatures & Models",
      "started_at": "2026-03-24T04:46:04Z"
    }
  ]
}