{
  "timestamp": "2026-02-22T22:22:57.635Z",
  "live": [
    {
      "username": "AlveusSanctuary",
      "title": "Animal Ambassador 24/7 Live Cams | !alveus !institute !pixel !schedule !video !feed",
      "game": "Animals, Aquariums, and Zoos",
      "started_at": "2026-02-22T14:40:57Z"
    },
    {
      "username": "Zachap",
      "title": "Looking for Real Gamers",
      "game": "Just Chatting",
      "started_at": "2026-02-22T10:02:43Z"
    },
    {
      "username": "VolcanoDoc",
      "title": "Trying to Balance with Basaltic Volcanism |🌋 Science Sunday | !phd !tkf !socials !pubs",
      "game": "Science & Technology",
      "started_at": "2026-02-22T21:51:23Z"
    },
    {
      "username": "Rocketology",
      "title": "How To Get Palatino & Antium Armor !sc !org",
      "game": "Star Citizen",
      "started_at": "2026-02-22T19:44:38Z"
    },
    {
      "username": "DrAlexanderClarke",
      "title": "Bruships 233: Science Fiction & Naval History Questions Answered Live...",
      "game": "Just Chatting",
      "started_at": "2026-02-22T19:31:47Z"
    }
  ]
}