{
  "timestamp": "2026-01-21T19:42:36.629Z",
  "live": [
    {
      "username": "Maya",
      "title": "🔴INSANE CONTENT TODAY🔴BIG FUN🔴",
      "game": "Just Chatting",
      "started_at": "2026-01-21T16:30:48Z"
    },
    {
      "username": "AlveusSanctuary",
      "title": "Projects w/ Dan | !alveus !institute !pixel !schedule !video !feed",
      "game": "Just Chatting",
      "started_at": "2026-01-20T13:38:52Z"
    },
    {
      "username": "EJ_SA",
      "title": "Fixing my snowblower before the big one hits!",
      "game": "Science & Technology",
      "started_at": "2026-01-21T16:36:15Z"
    },
    {
      "username": "Zachap",
      "title": "everything is silly, boomers are destroying everything :(",
      "game": "Just Chatting",
      "started_at": "2026-01-21T10:00:48Z"
    },
    {
      "username": "eToThe2iPi",
      "title": "Improving Mathematics Curriculum: Differential Equations",
      "game": "Math",
      "started_at": "2026-01-21T18:56:13Z"
    },
    {
      "username": "Stephen_Wolfram",
      "title": "Live CEOing Ep 965: Language Design in Wolfram Language [Normal/Ordinal, ArrayTrim and more]",
      "game": "Science & Technology",
      "started_at": "2026-01-21T19:28:16Z"
    },
    {
      "username": "PotteryDojo",
      "title": "Pottery: Making Bonsai Pots | Foot Stream | Batch # 19 | Batch Total: 25",
      "game": "Art",
      "started_at": "2026-01-21T18:15:05Z"
    }
  ]
}