{
  "timestamp": "2026-03-05T01:20:07.828Z",
  "live": [
    {
      "username": "AlveusSanctuary",
      "title": "Animal Ambassador 24/7 Live Cams | !alveus !institute !pixel !schedule !video !feed",
      "game": "Animals, Aquariums, and Zoos",
      "started_at": "2026-03-03T17:09:08Z"
    },
    {
      "username": "Paleontologizing",
      "title": "🦖 FOSSIL NEWS 🦴📰 Weird relic amphibian-y critter in Brazil, primate ancestor in Colorado + much more (w/ paleontologist Danny Anduza)",
      "game": "Science & Technology",
      "started_at": "2026-03-04T21:09:44Z"
    },
    {
      "username": "ipaintbirbs",
      "title": "bird of da day: wood duck",
      "game": "Art",
      "started_at": "2026-03-04T23:59:19Z"
    },
    {
      "username": "Zachap",
      "title": "Proletarian Politics | Educate our intelligence | Agitate our enthusiasm | Organize our force | No War but Class War | Learning and Teaching",
      "game": "Just Chatting",
      "started_at": "2026-03-04T10:01:26Z"
    },
    {
      "username": "nogre0",
      "title": "philosophyzing again",
      "game": "Just Chatting",
      "started_at": "2026-03-05T01:00:25Z"
    },
    {
      "username": "SharkG33k",
      "title": "Water Wednesday! 360 Caribbean reef sharks! 🦈",
      "game": "Science & Technology",
      "started_at": "2026-03-05T01:06:22Z"
    },
    {
      "username": "nSimplexPachinko",
      "title": "Trying to figure out a project: Galactic Coordinates. Taking requests on Math!",
      "game": "Math",
      "started_at": "2026-03-05T01:08:57Z"
    }
  ]
}