{
  "timestamp": "2026-02-25T23:01:27.874Z",
  "live": [
    {
      "username": "AlveusSanctuary",
      "title": "Animal Ambassador 24/7 Live Cams | !alveus !institute !pixel !schedule !video !feed",
      "game": "Animals, Aquariums, and Zoos",
      "started_at": "2026-02-25T21:09:55Z"
    },
    {
      "username": "EJ_SA",
      "title": "EJ's Space and SLS Rollback Revue! 2/25/26",
      "game": "Science & Technology",
      "started_at": "2026-02-25T19:05:47Z"
    },
    {
      "username": "Paleontologizing",
      "title": "FOSSIL NEWS 🦖 T. rex ran like a bird 🐔 Alvarezsaur evolution shake-up 🧬 4-eyed vertebrate ancestors 👓 (w/ paleontologist Danny Anduza)",
      "game": "Science & Technology",
      "started_at": "2026-02-25T21:05:21Z"
    },
    {
      "username": "JapanesePrintmaking",
      "title": "Making Japanese woodblock prints ... live while you watch ...",
      "game": "Makers & Crafting",
      "started_at": "2026-02-25T22:59:54Z"
    },
    {
      "username": "AdamLearnsLive",
      "title": "Delighting players 💎 (day 312½)",
      "game": "Software and Game Development",
      "started_at": "2026-02-25T21:44:33Z"
    },
    {
      "username": "Stephen_Wolfram",
      "title": "Stephen Wolfram: What Ultimately Is There? Metaphysics and the Ruliad",
      "game": "Science & Technology",
      "started_at": "2026-02-25T20:51:50Z"
    },
    {
      "username": "imreallyimportant",
      "title": "MISSING EPSTEIN FILES RELATED TO TRUMP ACCUSATIONS | SOTU REACTIONS",
      "game": "Just Chatting",
      "started_at": "2026-02-25T22:54:41Z"
    },
    {
      "username": "DrawCuriosity",
      "title": "🌊MERMAID --> MEDUSA COSPLAY. Turn me into Medusa 100 bits at a time - 100 bits = 1 HAIR TIE✨🐑 !dailybug !merch !tangia",
      "game": "Just Chatting",
      "started_at": "2026-02-25T22:44:40Z"
    },
    {
      "username": "Rocketology",
      "title": "Gunpowder Messiahs Career Continues!",
      "game": "MechWarrior 5: Mercenaries",
      "started_at": "2026-02-25T19:06:24Z"
    },
    {
      "username": "nSimplexPachinko",
      "title": "Cracking the GRE Math Subject Test, Night 034: Calc II \"Final Exam\"",
      "game": "Math",
      "started_at": "2026-02-25T22:42:49Z"
    }
  ]
}