{
  "timestamp": "2026-06-30T03:52:51.628Z",
  "live": [
    {
      "username": "AlveusSanctuary",
      "title": "Alveus Subathon (Day 37 / 43+) | !alveus !institute !pixel !schedule !video !subathon",
      "game": "Just Chatting",
      "started_at": "2026-06-29T13:01:24Z"
    },
    {
      "username": "Moohoodles",
      "title": "🪐 Astrobiology & Space News! ✨",
      "game": "Science & Technology",
      "started_at": "2026-06-30T01:12:08Z"
    },
    {
      "username": "DrawCuriosity",
      "title": "🌎[PARTNER PUSH (2 left!)] Meccha Chameleon with @Xanthe @MartubyMartu @LakeSpookie @peybtw @AaronSchmitz ✨🐏 !merch !dailybug !wcr",
      "game": "MECCHA CHAMELEON",
      "started_at": "2026-06-30T00:30:07Z"
    },
    {
      "username": "SciAnts_Streams",
      "title": "[Charity Event For Cancer Research] | Raising money for Fredhutch Cancer Research Center | Partner+ 307/300 | !ppp !yt !pod !fredhutch",
      "game": "Science & Technology",
      "started_at": "2026-06-30T00:59:30Z"
    }
  ]
}