{
  "timestamp": "2026-01-23T16:50:12.753Z",
  "live": [
    {
      "username": "AlveusSanctuary",
      "title": "Animal Ambassador 24/7 Live Cams | !alveus !institute !pixel !schedule !video !feed",
      "game": "Animals, Aquariums, and Zoos",
      "started_at": "2026-01-22T13:38:54Z"
    },
    {
      "username": "Zachap",
      "title": "TRUMP PROTESTING ACAB VENEZUELA CHINA GREENLAND DRUGS PALESTINE COMMUNISM EDUCATION AI ARTIFICIAL INTELLIGENCE CLIMATE CHANGE UNBOXING NEWS",
      "game": "Just Chatting",
      "started_at": "2026-01-23T10:04:57Z"
    },
    {
      "username": "AdamLearnsLive",
      "title": "Game dev for Skeleseller (day 294)",
      "game": "Software and Game Development",
      "started_at": "2026-01-23T16:27:48Z"
    },
    {
      "username": "EJ_SA",
      "title": "Fixing a snow blower and generator before a big storm!",
      "game": "Science & Technology",
      "started_at": "2026-01-23T16:47:29Z"
    },
    {
      "username": "TimberAnew",
      "title": "Carving books n ropes",
      "game": "Art",
      "started_at": "2026-01-23T15:02:24Z"
    },
    {
      "username": "ProfessorEXP",
      "title": "Education |  Snowmagedon | Inclusive Design | Society and Culture",
      "game": "Just Chatting",
      "started_at": "2026-01-23T13:59:38Z"
    }
  ]
}