{
  "timestamp": "2026-04-30T00:26:08.758Z",
  "live": [
    {
      "username": "AlveusSanctuary",
      "title": "Animal Ambassador 24/7 Live Cams | !alveus !institute !schedule !video",
      "game": "Animals, Aquariums, and Zoos",
      "started_at": "2026-04-28T15:20:29Z"
    },
    {
      "username": "EJ_SA",
      "title": "Giving SLS the upper stage it deserves!",
      "game": "Kerbal Space Program",
      "started_at": "2026-04-29T17:36:19Z"
    },
    {
      "username": "JapanesePrintmaking",
      "title": "Making Japanese woodblock prints ... live while you watch ...",
      "game": "Makers & Crafting",
      "started_at": "2026-04-29T23:13:23Z"
    },
    {
      "username": "imreallyimportant",
      "title": "COMBATIVE HOUSE HEARING WITH PETE HEGSETH | SC WEAKENS VRA | POWELL TO STAY ON FED BOARD",
      "game": "Just Chatting",
      "started_at": "2026-04-29T21:54:38Z"
    },
    {
      "username": "ipaintbirbs",
      "title": "a sweet evening with the birbs",
      "game": "Art",
      "started_at": "2026-04-29T23:12:38Z"
    },
    {
      "username": "Paleontologizing",
      "title": "FOSSIL SCIENCE NEWS 🦕📰 What's new in the world of paleontology, plus viewer Q&A and more (w/ paleontologist Danny Anduza) !WYwishlist",
      "game": "Science & Technology",
      "started_at": "2026-04-29T20:05:06Z"
    },
    {
      "username": "SciAnts_Streams",
      "title": "🌘 SAROS Time 🌒| Eclipse science, animals, and rabbit holes galore | Partner+ 328/300 | !ppp !yt !pod !gotel",
      "game": "SAROS",
      "started_at": "2026-04-29T18:01:32Z"
    },
    {
      "username": "nogre0",
      "title": "responding to philosophy referees",
      "game": "Just Chatting",
      "started_at": "2026-04-30T00:00:33Z"
    },
    {
      "username": "SharkG33k",
      "title": "Water Wednesday! Trash clean up 360 dive videos! 🪸",
      "game": "Science & Technology",
      "started_at": "2026-04-30T00:01:52Z"
    }
  ]
}