{
  "timestamp": "2025-12-17T18:46:21.859Z",
  "live": [
    {
      "username": "Kitboga",
      "title": "Don't Buy AI Cars [Ep 1501]",
      "game": "Just Chatting",
      "started_at": "2025-12-17T16:30:16Z"
    },
    {
      "username": "AlveusSanctuary",
      "title": "Animal Ambassador 24/7 Live Cams | !alveus !institute !pixel !schedule !video !feed",
      "game": "Animals, Aquariums, and Zoos",
      "started_at": "2025-12-17T13:26:02Z"
    },
    {
      "username": "EJ_SA",
      "title": "Replacing a wheelhouse on a 69 coronet! The Crew Cab Charger (Part 41)",
      "game": "IRL",
      "started_at": "2025-12-17T14:54:42Z"
    },
    {
      "username": "ArchitectureTV",
      "title": "MONTREAL winter road trip day 02🎄Historic and contemporary buildings | Architecture IRL",
      "game": "IRL",
      "started_at": "2025-12-17T15:59:20Z"
    },
    {
      "username": "AdamLearnsLive",
      "title": "Okay but for real, we're achieving stuff (day 279)",
      "game": "Software and Game Development",
      "started_at": "2025-12-17T16:22:30Z"
    },
    {
      "username": "Zachap",
      "title": "do we live in an age of Gerontofascism?",
      "game": "Just Chatting",
      "started_at": "2025-12-17T13:57:43Z"
    },
    {
      "username": "pencenter",
      "title": "SMW 96* Run with @etothe2ipi [!dp when penn dies, !dz when zach dies]",
      "game": "Super Mario World",
      "started_at": "2025-12-17T17:30:59Z"
    }
  ]
}