{
  "timestamp": "2026-04-21T23:35:52.053Z",
  "live": [
    {
      "username": "AlveusSanctuary",
      "title": "Animal Ambassador 24/7 Live Cams | !alveus !institute !pixel !schedule !video",
      "game": "Animals, Aquariums, and Zoos",
      "started_at": "2026-04-20T05:01:56Z"
    },
    {
      "username": "EJ_SA",
      "title": "EJ's Space and Rocket Revue! 4/21/26",
      "game": "Science & Technology",
      "started_at": "2026-04-21T17:51:01Z"
    },
    {
      "username": "imreallyimportant",
      "title": "LIVE: VIRGINIA ELECTION RESULTS",
      "game": "Just Chatting",
      "started_at": "2026-04-21T21:54:37Z"
    },
    {
      "username": "Paleontologizing",
      "title": "🌊🦕📷 'LOCH NESS MONSTER' discussion 💬 on the 92nd anniversary of famous \"Surgeon's Photo\" publication (w/ paleontologist Danny Anduza)",
      "game": "Science & Technology",
      "started_at": "2026-04-21T20:06:14Z"
    },
    {
      "username": "eToThe2iPi",
      "title": "How Aligned Are You: A Vector Story (and Should This Video Go On YouTube?)",
      "game": "Math",
      "started_at": "2026-04-21T22:06:01Z"
    },
    {
      "username": "MelissaInDeNile",
      "title": "Let's play more Assassin's Creed 3!!!! What historical figure will we run into next?? ~ Follower Goal: 2339/2600 ~ !socials !beyonddenile",
      "game": "Assassin's Creed III Remastered",
      "started_at": "2026-04-21T22:50:45Z"
    }
  ]
}