{
  "timestamp": "2025-11-29T00:21:46.762Z",
  "live": [
    {
      "username": "AlveusSanctuary",
      "title": "[Badges] #TogetherForGood Animal Ambassador 24/7 Live Cams | !alveus !institute !pixel !badge !schedule !video !feed",
      "game": "Animals, Aquariums, and Zoos",
      "started_at": "2025-11-28T15:25:48Z"
    },
    {
      "username": "imreallyimportant",
      "title": "TRUMP CLAIMS TO TERMINATE BIDEN-ERA DOCS SIGNED BY AUTOPEN (??)",
      "game": "Just Chatting",
      "started_at": "2025-11-28T22:59:34Z"
    },
    {
      "username": "AstroCanuck",
      "title": "Live Astrophotography: Clear skies now, but clouds later| !mo !moch | TWO T3 MINIFIGS LEFT !pp !upgrade !drop !tkf",
      "game": "Science & Technology",
      "started_at": "2025-11-28T23:49:51Z"
    },
    {
      "username": "Zachap",
      "title": "Come and learn if you want :)",
      "game": "Politics",
      "started_at": "2025-11-28T10:01:34Z"
    },
    {
      "username": "DrMick",
      "title": "PIZZA DELIVERY MADNESS | 40k Death Guard vs. Imperial Guard",
      "game": "Miniatures & Models",
      "started_at": "2025-11-28T22:49:45Z"
    },
    {
      "username": "shnaff",
      "title": "chill instrumental piano",
      "game": "Music",
      "started_at": "2025-11-28T23:02:24Z"
    },
    {
      "username": "nSimplexPachinko",
      "title": "Elite Dangerous, Night 0058: New Community Goal: INTERFERE with HIP 87621 !",
      "game": "Elite: Dangerous",
      "started_at": "2025-11-28T22:45:38Z"
    }
  ]
}