{
  "timestamp": "2026-07-14T18:28:30.173Z",
  "live": [
    {
      "username": "AlveusSanctuary",
      "title": "Animal Care Chats | !alveus !institute !pixel !schedule !video",
      "game": "Just Chatting",
      "started_at": "2026-07-13T13:01:43Z"
    },
    {
      "username": "EJ_SA",
      "title": "EJ's Space and Rocket Revue! 7/14/26",
      "game": "Science & Technology",
      "started_at": "2026-07-14T14:32:15Z"
    },
    {
      "username": "ipaintbirbs",
      "title": "the duck days are over* (*just beginning, today)",
      "game": "Art",
      "started_at": "2026-07-14T16:01:56Z"
    },
    {
      "username": "oh_bother",
      "title": "Jules is here to do synthesizer stuff! Soldering Eurorack and junk.",
      "game": "Science & Technology",
      "started_at": "2026-07-14T16:23:17Z"
    },
    {
      "username": "Zachap",
      "title": "Schrödinger's ceasefire, Trump's war.",
      "game": "Just Chatting",
      "started_at": "2026-07-14T10:02:29Z"
    },
    {
      "username": "Rocketology",
      "title": "1/4 Real Scale Kareer - Episode 2",
      "game": "Kerbal Space Program",
      "started_at": "2026-07-14T18:17:52Z"
    }
  ]
}