{
  "timestamp": "2026-01-12T04:39:03.384Z",
  "live": [
    {
      "username": "AlveusSanctuary",
      "title": "Animal Ambassador 24/7 Live Cams | !alveus !institute !pixel !schedule !video !feed",
      "game": "Animals, Aquariums, and Zoos",
      "started_at": "2026-01-10T13:35:47Z"
    },
    {
      "username": "SciAnts_Streams",
      "title": "SciAnts Sunday | Hunting tiny worlds in Grounded 2 and chatting science | Partner+ 122/300 | !ppp !yt !pod",
      "game": "Grounded 2",
      "started_at": "2026-01-12T01:58:20Z"
    },
    {
      "username": "happyknightmares",
      "title": "Studying synesthesia and co-working! 🎨🧠",
      "game": "Science & Technology",
      "started_at": "2026-01-12T02:43:55Z"
    },
    {
      "username": "walkingsticklibrary",
      "title": "The Jello Trick. Who is Rachel Celler, and the physiology of whale strandings.",
      "game": "IRL",
      "started_at": "2026-01-12T02:30:17Z"
    }
  ]
}