{
  "timestamp": "2025-12-31T16:21:38.581Z",
  "live": [
    {
      "username": "AlveusSanctuary",
      "title": "Animal Ambassador 24/7 Live Cams | !alveus !institute !pixel !schedule !video !feed",
      "game": "Animals, Aquariums, and Zoos",
      "started_at": "2025-12-31T13:32:57Z"
    },
    {
      "username": "Zachap",
      "title": "its 2026 here",
      "game": "Just Chatting",
      "started_at": "2025-12-31T10:03:03Z"
    },
    {
      "username": "TimberAnew",
      "title": "Carving the Needle Archer",
      "game": "Art",
      "started_at": "2025-12-31T15:00:26Z"
    }
  ]
}