{
  "timestamp": "2026-02-06T03:59:08.113Z",
  "live": [
    {
      "username": "AlveusSanctuary",
      "title": "Animal Ambassador 24/7 Live Cams | !alveus !institute !pixel !schedule !video !feed",
      "game": "Animals, Aquariums, and Zoos",
      "started_at": "2026-02-04T14:39:16Z"
    },
    {
      "username": "SciAnts_Streams",
      "title": "Pokémon Legends Science - First Playthrough | The science of Pokémon as we catch them all! | Partner+ 58/300 | !ppp !yt !pod",
      "game": "Pokémon Legends: Z-A",
      "started_at": "2026-02-05T19:01:55Z"
    },
    {
      "username": "Nerduino",
      "title": "There's no black hole at the center of the Milky Way? PhD Astronomer.  Former NASA guy  #science #space #stem #nasa",
      "game": "Science & Technology",
      "started_at": "2026-02-06T01:53:39Z"
    },
    {
      "username": "DrawCuriosity",
      "title": "🐝PhD in Insect Flight plays Bee Sim for the first time!✨🐑 !merch !louse !dailybug",
      "game": "Bee Simulator",
      "started_at": "2026-02-05T22:27:32Z"
    },
    {
      "username": "SydHeresy",
      "title": "Soldering For Science - Electronics",
      "game": "Science & Technology",
      "started_at": "2026-02-05T19:00:52Z"
    },
    {
      "username": "MelissaInDeNile",
      "title": "LAST!!! Lego Pirates of the Cairbbean!!!~ Follower Goal: 2248/2300 ~ !socials !beyonddenile",
      "game": "LEGO Pirates of the Caribbean: The Video Game",
      "started_at": "2026-02-06T02:43:35Z"
    },
    {
      "username": "SharkG33k",
      "title": "Clean Up Earth!",
      "game": "Clean Up Earth",
      "started_at": "2026-02-06T01:02:55Z"
    },
    {
      "username": "walkingsticklibrary",
      "title": "Feline compulsive disorder, who is Paul Whiteman, and Brumese pythons out in the cold.",
      "game": "IRL",
      "started_at": "2026-02-06T02:25:17Z"
    },
    {
      "username": "happyknightmares",
      "title": "Got conditionally accepted for a Masters in Design! :D Studying synesthesia, co-working and chatting! 🎨🧠 What are you working on? Tell us!",
      "game": "Co-working & Studying",
      "started_at": "2026-02-06T02:48:35Z"
    }
  ]
}