{
  "timestamp": "2026-03-24T22:29:46.929Z",
  "live": [
    {
      "username": "AlveusSanctuary",
      "title": "Animal Ambassador 24/7 Live Cams | !alveus !institute !pixel !schedule !video !feed",
      "game": "Animals, Aquariums, and Zoos",
      "started_at": "2026-03-23T15:24:58Z"
    },
    {
      "username": "Paleontologizing",
      "title": "🐢 TURTLE TUESDAY 🐢 Discussing the biology, evolution, & conservation of LEATHERBACK TURTLES +more 💊 Still fighting off ear infection 🤒",
      "game": "Science & Technology",
      "started_at": "2026-03-24T20:31:30Z"
    },
    {
      "username": "imreallyimportant",
      "title": "TRUMP CLAIMS PEACE TALKS WITH IRAN ARE HAPPENING | SENATE DEMS REJECT GOP OFFER TO FUND DHS",
      "game": "Just Chatting",
      "started_at": "2026-03-24T21:49:37Z"
    },
    {
      "username": "AdamLearnsLive",
      "title": "Paying [tech] debt",
      "game": "Software and Game Development",
      "started_at": "2026-03-24T18:59:45Z"
    },
    {
      "username": "Zachap",
      "title": "wealthy people are morally broke",
      "game": "Just Chatting",
      "started_at": "2026-03-24T10:01:24Z"
    },
    {
      "username": "shnaff",
      "title": "Guitar, piano, and singing in !stereo🎧",
      "game": "Music",
      "started_at": "2026-03-24T22:02:31Z"
    },
    {
      "username": "SydHeresy",
      "title": "Making Synths And Fixing Stuff - Electronics - DIY",
      "game": "Science & Technology",
      "started_at": "2026-03-24T19:30:04Z"
    },
    {
      "username": "GeoJim2006",
      "title": "Geologizing from the NOVA geology lab 🌋⚒️🪨🔎🔬 !discord !nova !tkf",
      "game": "Science & Technology",
      "started_at": "2026-03-24T19:47:07Z"
    },
    {
      "username": "xTalkProgrammer",
      "title": "Leer Nederlands (NT2) | NL EN DE | !socs !ai !disc !lcbk",
      "game": "Just Chatting",
      "started_at": "2026-03-24T20:29:51Z"
    }
  ]
}