{
  "timestamp": "2025-12-01T01:11:36.008Z",
  "live": [
    {
      "username": "AlveusSanctuary",
      "title": "[Badges] #TogetherForGood Animal Ambassador 24/7 Live Cams | !alveus !institute !pixel !badge !schedule !video !feed",
      "game": "Animals, Aquariums, and Zoos",
      "started_at": "2025-11-30T00:19:05Z"
    },
    {
      "username": "shnaff",
      "title": "chill instrumental music",
      "game": "Music",
      "started_at": "2025-11-30T23:02:36Z"
    },
    {
      "username": "MelissaInDeNile",
      "title": "Drifting Down De Nile Discussion Stream! Tomb DB320 and Christmas Tree Decorating!! ~ Follower Goal: 2223/2300 ~ !socials !beyonddenile",
      "game": "Just Chatting",
      "started_at": "2025-12-01T00:20:41Z"
    },
    {
      "username": "ActualEducation",
      "title": "FREE Tutoring in Math/Science - Actual Education: Office Hours",
      "game": "Just Chatting",
      "started_at": "2025-11-30T23:09:23Z"
    }
  ]
}