{
  "timestamp": "2026-04-24T00:05:37.357Z",
  "live": [
    {
      "username": "AlveusSanctuary",
      "title": "Animal Ambassador 24/7 Live Cams | !alveus !institute !pixel !schedule !video",
      "game": "Animals, Aquariums, and Zoos",
      "started_at": "2026-04-22T19:28:51Z"
    },
    {
      "username": "Paleontologizing",
      "title": "🦕⁉ DINOSAUR Q&A + Thursday Birdsday 🐧 (w/ paleontologist Danny Anduza) 🦖 Discussing 'kraken' fossil discovery on BONUS STREAM tomorrow 🐙",
      "game": "Science & Technology",
      "started_at": "2026-04-23T20:04:01Z"
    },
    {
      "username": "SciAnts_Streams",
      "title": "Mouse: PI for Hire | Learning and memory mouse science with #MOUSEPIForHire #keymailer | Partner+ 247/300 | !ppp !yt !pod !wwf",
      "game": "Mouse: P.I. For Hire",
      "started_at": "2026-04-23T18:27:08Z"
    },
    {
      "username": "DrawCuriosity",
      "title": "🎉 [SUBATHON - TWISTER] LET'S GET DR. INÉS TO SINGAPORE!!  !subathon !tip (tips, donos, fourthwall, bits, subs ALL ADD TO THE TIMER) 👀 ✨🐑",
      "game": "Special Events",
      "started_at": "2026-04-23T19:55:23Z"
    },
    {
      "username": "Zachap",
      "title": "is my mic audio clear? hopefully, also private property is unjustifiable",
      "game": "Just Chatting",
      "started_at": "2026-04-23T10:02:31Z"
    },
    {
      "username": "shnaff",
      "title": "Guitar, piano, and singing in !stereo🎧",
      "game": "Music",
      "started_at": "2026-04-23T22:00:47Z"
    },
    {
      "username": "MelissaInDeNile",
      "title": "Beyond De Nile Guest Lecture with @sharkg33k! Talking about sharks and conservation! ~ Follower Goal: 2339/2600 ~ !socials !beyonddenile",
      "game": "Just Chatting",
      "started_at": "2026-04-23T22:49:49Z"
    },
    {
      "username": "SharkG33k",
      "title": "Beyond de Nile Lecture Series with @melissaindenile",
      "game": "Science & Technology",
      "started_at": "2026-04-23T22:50:34Z"
    },
    {
      "username": "nSimplexPachinko",
      "title": "TTRPG Planning: TitansGrave 006: Players' Forlorn Hope",
      "game": "Tabletop RPGs",
      "started_at": "2026-04-23T21:43:38Z"
    }
  ]
}