{
  "timestamp": "2026-02-14T05:02:45.748Z",
  "live": [
    {
      "username": "AlveusSanctuary",
      "title": "Animal Ambassador 24/7 Live Cams | !alveus !institute !pixel !schedule !video !feed",
      "game": "Animals, Aquariums, and Zoos",
      "started_at": "2026-02-12T14:39:26Z"
    },
    {
      "username": "EJ_SA",
      "title": "WE HAVE DRONES! THE FACTORY MUST GROW!! Factorio (Part 7)",
      "game": "Factorio",
      "started_at": "2026-02-13T22:17:09Z"
    },
    {
      "username": "imreallyimportant",
      "title": "PARTIAL GOVERNMENT SHUTDOWN IMMINENT | DESTINY UFA SOUTH CAROLINA",
      "game": "Just Chatting",
      "started_at": "2026-02-13T22:59:37Z"
    },
    {
      "username": "Moohoodles",
      "title": "🪐 Happy VDay! ✨ Dating Everything! :) NMS later !pp",
      "game": "Date Everything!",
      "started_at": "2026-02-14T02:41:09Z"
    },
    {
      "username": "SciAnts_Streams",
      "title": "Valentine's SciAnts News | New species, snails, frogs, plants, termites and more! | Partner+ 133/300 | !ppp !yt !pod",
      "game": "Science & Technology",
      "started_at": "2026-02-14T02:02:23Z"
    },
    {
      "username": "AstroCanuck",
      "title": "Week's End Catchup: Space News & LEGO Tudor Corner Concludes | !PGV !light !texas | !drop !tkf",
      "game": "Science & Technology",
      "started_at": "2026-02-14T01:01:18Z"
    },
    {
      "username": "Mr_Aejis",
      "title": "Teacher Plays: Honkai Star Rail!",
      "game": "Honkai: Star Rail",
      "started_at": "2026-02-14T01:38:02Z"
    },
    {
      "username": "pencenter",
      "title": "ZOoTR nearly max settings. we are in for the night... [!fish🎣|!commands💻]",
      "game": "The Legend of Zelda: Ocarina of Time",
      "started_at": "2026-02-14T04:32:15Z"
    }
  ]
}