{
  "timestamp": "2026-03-22T05:42:19.914Z",
  "live": [
    {
      "username": "AlveusSanctuary",
      "title": "Animal Ambassador 24/7 Live Cams | !alveus !institute !pixel !schedule !video !feed",
      "game": "Animals, Aquariums, and Zoos",
      "started_at": "2026-03-21T14:32:34Z"
    },
    {
      "username": "DrMick",
      "title": "Therapist Plays GTA IV: Part 28",
      "game": "Grand Theft Auto IV",
      "started_at": "2026-03-22T05:06:41Z"
    },
    {
      "username": "SydHeresy",
      "title": "Eurorack Modules - Cases - DIY - Electronics - Soldering",
      "game": "Science & Technology",
      "started_at": "2026-03-21T21:20:18Z"
    },
    {
      "username": "TominationTime",
      "title": "🔴FF8 REMAKE FEAT. Thomas The Tank🔴SHE WILL SCREAM",
      "game": "Resident Evil 2",
      "started_at": "2026-03-22T03:43:01Z"
    }
  ]
}